pywe_component/__init__.py
pywe_component/component.py
pywe_component-1.0.1.dist-info/METADATA
pywe_component-1.0.1.dist-info/WHEEL
pywe_component-1.0.1.dist-info/top_level.txt
pywe_component-1.0.1.dist-info/RECORD
